constance/__init__.py
constance/admin.py
constance/config.py
constance/context_processors.py
constance/models.py
constance/settings.py
constance/utils.py
constance/backends/__init__.py
constance/backends/redisd.py
constance/backends/database/__init__.py
constance/backends/database/models.py
constance/backends/database/migrations/0001_initial.py
constance/backends/database/migrations/0002_auto__chg_field_constance_key__add_unique_constance_key.py
constance/backends/database/migrations/__init__.py
constance/locale/de/LC_MESSAGES/django.mo
constance/locale/de/LC_MESSAGES/django.po
constance/locale/en/LC_MESSAGES/django.mo
constance/locale/en/LC_MESSAGES/django.po
constance/locale/pl/LC_MESSAGES/django.mo
constance/locale/pl/LC_MESSAGES/django.po
constance/locale/ru/LC_MESSAGES/django.mo
constance/locale/ru/LC_MESSAGES/django.po
constance/templates/admin/constance/change_list.html
constance/templatetags/__init__.py
constance/templatetags/constance_tags.py
django_constance_trbs-0.7.9.dist-info/DESCRIPTION.rst
django_constance_trbs-0.7.9.dist-info/METADATA
django_constance_trbs-0.7.9.dist-info/metadata.json
django_constance_trbs-0.7.9.dist-info/pbr.json
django_constance_trbs-0.7.9.dist-info/RECORD
django_constance_trbs-0.7.9.dist-info/top_level.txt
django_constance_trbs-0.7.9.dist-info/WHEEL
