Metadata-Version: 2.0
Name: django-constance-trbs
Version: 0.7.9
Summary: Django live settings with pluggable backends, including Redis.
Home-page: http://github.com/trbs/django-constance-trbs
Author: Jannis Leidel
Author-email: jannis@leidel.info
License: BSD
Keywords: django,libraries,settings,redis
Platform: any
Classifier: Development Status :: 5 - Production/Stable
Classifier: Environment :: Web Environment
Classifier: Framework :: Django
Classifier: Intended Audience :: Developers
Classifier: Natural Language :: English
Classifier: License :: OSI Approved :: BSD License
Classifier: Operating System :: OS Independent
Classifier: Programming Language :: Python
Classifier: Programming Language :: Python :: 3
Classifier: Programming Language :: Python :: Implementation :: PyPy
Classifier: Topic :: Utilities
Requires-Dist: six
Provides-Extra: database
Requires-Dist: django-picklefield; extra == 'database'
Provides-Extra: redis
Requires-Dist: redis; extra == 'redis'
